lk_stat_package/__init__.py
lk_stat_package/lk_stat.c
lk_stat_package/lk_stat.cpython-39-darwin.so
lk_stat_package/lk_stat.pyx
lk_stat_package/lk_stat_old.pyx
lk_stat_package/lk_stat_old_2.pyx
lk_stat_package-0.1.4.dist-info/METADATA
lk_stat_package-0.1.4.dist-info/WHEEL
lk_stat_package-0.1.4.dist-info/top_level.txt
lk_stat_package-0.1.4.dist-info/RECORD
