Metadata-Version: 2.4
Name: lk_stat_package
Version: 0.1.4
Summary: A Cython-based package for computing the Laffler-Kinman statistic.
Author: Princy Ranaivomanana
Author-email: rtprincy@gmail.com
Platform: manylinux2014_x86_64
Classifier: Programming Language :: Python
Classifier: Programming Language :: Python :: 3
Classifier: Programming Language :: Cython
Classifier: License :: OSI Approved :: MIT License
Classifier: Operating System :: POSIX :: Linux
Requires-Dist: numpy
Requires-Dist: cython
Dynamic: author
Dynamic: author-email
Dynamic: classifier
Dynamic: description
Dynamic: description-content-type
Dynamic: platform
Dynamic: requires-dist
Dynamic: summary
